utilsd/__init__.py
utilsd/avgmeter.py
utilsd/earlystop.py
utilsd/experiment.py
utilsd/logging.py
utilsd/analysis/__init__.py
utilsd/analysis/__main__.py
utilsd/analysis/builtins.py
utilsd/analysis/pattern.py
utilsd/analysis/pipeline.py
utilsd/analysis/utils.py
utilsd/az/__init__.py
utilsd/az/cli.py
utilsd/az/utils.py
utilsd/config/__init__.py
utilsd/config/builtin.py
utilsd/config/cli_parser.py
utilsd/config/exception.py
utilsd/config/python.py
utilsd/config/registry.py
utilsd/config/type_def.py
utilsd/fileio/__init__.py
utilsd/fileio/config.py
utilsd/fileio/io.py
utilsd/fileio/parse.py
utilsd/fileio/handlers/__init__.py
utilsd/fileio/handlers/base.py
utilsd/fileio/handlers/json_handler.py
utilsd/fileio/handlers/pickle_handler.py
utilsd/fileio/handlers/yaml_handler.py
utilsd/search/__init__.py
utilsd/search/confext.py
utilsd/search/confgen.py
utilsd/search/space.py
utilsd-0.0.18.post0.dist-info/LICENSE
utilsd-0.0.18.post0.dist-info/METADATA
utilsd-0.0.18.post0.dist-info/WHEEL
utilsd-0.0.18.post0.dist-info/entry_points.txt
utilsd-0.0.18.post0.dist-info/top_level.txt
utilsd-0.0.18.post0.dist-info/RECORD
