Metadata-Version: 2.1
Name: utilsd
Version: 0.0.18.post0
Summary: Common utils for deep learning.
Home-page: https://github.com/ultmaster/utilsd
Author: Yuge Zhang
Author-email: scottyugochang@gmail.com
Classifier: Programming Language :: Python :: 3
Classifier: License :: OSI Approved :: MIT License
Classifier: Operating System :: OS Independent
Requires-Python: >=3.7
License-File: LICENSE
Requires-Dist: addict (>=2.4.0)
Requires-Dist: click (>=7.0)
Requires-Dist: numpy (>=1.18.0)
Requires-Dist: pyyaml (>=5.4.1)
Requires-Dist: yapf (>=0.31.0)
Requires-Dist: typeguard (<3.0,>=2.13)
Requires-Dist: numpy (<1.22) ; python_version < "3.8"
Requires-Dist: typing-extensions (>=3.7) ; python_version < "3.8"
Provides-Extra: docs
Requires-Dist: sphinx ; extra == 'docs'
Requires-Dist: nbsphinx ; extra == 'docs'
Requires-Dist: pydata-sphinx-theme ; extra == 'docs'
Requires-Dist: ipython ; extra == 'docs'
Provides-Extra: full
Requires-Dist: torch (>=1.7.1) ; extra == 'full'
